{
  "name": "Vortex Mod Manager Turkish Localization 2024",
  "author": "binzedd - Ilker BINZET",
  "version": "1.5.7",
  "description": "Vortex Mod Manager Turkish Localization 2024",
  "type": "translation",
  "bundled": false,
  "modId": 811,
  "modURL": "http://www.nexusmods.com/site/mods/811",
  "downloadURL": "http://www.nexusmods.com/site/mods/811/download",
  "modName": "Vortex Mod Manager Turkish Localization 2024",
  "modType": "translation",
  "locale": "tr",
  "localeCode": "tr_TR",
  "localeName": "Turkish",
  "GitHub": "https://github.com/ilker-binzet/Vortex-Mod-Manager-Turkish-Localization",
  "GitHubURL": "https://github.com/ilker-binzet/Vortex-Mod-Manager-Turkish-Localization",
  "GitHubRawURL": "https://raw.githubusercontent.com/ilker-binzet/Vortex-Mod-Manager-Turkish-Localization/main"
}